dataplotter/Models.py
dataplotter/__init__.py
dataplotter/__main__.py
dataplotter-0.0.16.dist-info/LICENSE.txt
dataplotter-0.0.16.dist-info/METADATA
dataplotter-0.0.16.dist-info/WHEEL
dataplotter-0.0.16.dist-info/top_level.txt
dataplotter-0.0.16.dist-info/RECORD
